cubicweb_book/__init__.py
cubicweb_book/__pkginfo__.py
cubicweb_book/entities.py
cubicweb_book/hooks.py
cubicweb_book/olapi.py
cubicweb_book/schema.py
cubicweb_book/site_cubicweb.py
cubicweb_book/uiprops.py
cubicweb_book/data/blue_arrow.png
cubicweb_book/data/cubes.book.css
cubicweb_book/data/cubes.book.js
cubicweb_book/data/default-cover.png
cubicweb_book/i18n/en.po
cubicweb_book/i18n/es.po
cubicweb_book/i18n/fr.po
cubicweb_book/migration/0.3.0_Any.py
cubicweb_book/migration/0.5.0_Any.py
cubicweb_book/migration/0.7.1_Any.py
cubicweb_book/migration/__init__.py
cubicweb_book/migration/import_dbpedia.py
cubicweb_book/migration/import_freebase.py
cubicweb_book/migration/import_ol.py
cubicweb_book/migration/postcreate.py
cubicweb_book/views/__init__.py
cubicweb_book/views/bibo.py
cubicweb_book/views/boxes.py
cubicweb_book/views/facet.py
cubicweb_book/views/primaries.py
cubicweb_book/views/secondaries.py
cubicweb_book/views/urls.py
cubicweb_book-1.1.1.dist-info/METADATA
cubicweb_book-1.1.1.dist-info/WHEEL
cubicweb_book-1.1.1.dist-info/entry_points.txt
cubicweb_book-1.1.1.dist-info/top_level.txt
cubicweb_book-1.1.1.dist-info/RECORD
